odoo/addons/website_sale_product_pack/README.rst
odoo/addons/website_sale_product_pack/__init__.py
odoo/addons/website_sale_product_pack/__manifest__.py
odoo/addons/website_sale_product_pack/i18n/website_sale_product_pack.pot
odoo/addons/website_sale_product_pack/models/__init__.py
odoo/addons/website_sale_product_pack/models/product_product.py
odoo/addons/website_sale_product_pack/models/product_template.py
odoo/addons/website_sale_product_pack/models/sale_order.py
odoo/addons/website_sale_product_pack/models/website.py
odoo/addons/website_sale_product_pack/readme/CONTRIBUTORS.rst
odoo/addons/website_sale_product_pack/readme/DESCRIPTION.rst
odoo/addons/website_sale_product_pack/readme/ROADMAP.rst
odoo/addons/website_sale_product_pack/readme/USAGE.rst
odoo/addons/website_sale_product_pack/static/description/icon.png
odoo/addons/website_sale_product_pack/static/description/index.html
odoo/addons/website_sale_product_pack/static/src/js/website_sale_product_pack_tour.js
odoo/addons/website_sale_product_pack/tests/__init__.py
odoo/addons/website_sale_product_pack/tests/test_website_sale_product_pack.py
odoo/addons/website_sale_product_pack/views/assets.xml
odoo/addons/website_sale_product_pack/views/templates.xml
odoo13_addon_website_sale_product_pack-13.0.1.0.3.dist-info/METADATA
odoo13_addon_website_sale_product_pack-13.0.1.0.3.dist-info/WHEEL
odoo13_addon_website_sale_product_pack-13.0.1.0.3.dist-info/top_level.txt
odoo13_addon_website_sale_product_pack-13.0.1.0.3.dist-info/RECORD
